socproof/__init__.py
socproof/__version__.py
socproof/models/__init__.py
socproof-0.0.1.dist-info/METADATA
socproof-0.0.1.dist-info/WHEEL
socproof-0.0.1.dist-info/top_level.txt
socproof-0.0.1.dist-info/RECORD
